{"nodes": [{"id": "unit_grace_test_suite", "label": "effectiveGrace unit test suite", "file_type": "code", "source_file": "web/tests/unit/grace.test.ts", "source_location": null, "source_url": null, "captured_at": null, "author": null, "contributor": null}, {"id": "concept_grace_lib", "label": "web/lib/grace.ts (effectiveGrace)", "file_type": "concept", "source_file": "web/tests/unit/grace.test.ts", "source_location": null, "source_url": null, "captured_at": null, "author": null, "contributor": null}], "edges": [{"source": "unit_grace_test_suite", "target": "concept_grace_lib", "relation": "references", "confidence": "EXTRACTED", "confidence_score": 1.0, "source_file": "web/tests/unit/grace.test.ts", "source_location": null, "weight": 1.0}, {"source": "concept_grace_lib", "target": "concept_reconcile_attendance_rpc", "relation": "semantically_similar_to", "confidence": "INFERRED", "confidence_score": 0.7, "source_file": "web/tests/unit/grace.test.ts", "source_location": null, "weight": 1.0}], "hyperedges": []}