{"nodes": [{"id": "syllabus_route_get", "label": "GET /api/syllabus (signed URL redirect for private class syllabus PDF)", "file_type": "code", "source_file": "web/app/api/syllabus/route.ts", "source_location": null, "source_url": null, "captured_at": null, "author": null, "contributor": null}, {"id": "issue_45_class_syllabus", "label": "Issue #45: open a class's syllabus PDF via signed URL", "file_type": "rationale", "source_file": "web/app/api/syllabus/route.ts", "source_location": null, "source_url": null, "captured_at": null, "author": null, "contributor": null, "rationale": "Same private-bucket signed-URL pattern as student-photo: authenticate as a School member, look up the RLS-scoped metadata row, mint a short-lived signed URL, redirect."}], "edges": [{"source": "syllabus_route_get", "target": "issue_45_class_syllabus", "relation": "references", "confidence": "EXTRACTED", "confidence_score": 1.0, "source_file": "web/app/api/syllabus/route.ts", "source_location": null, "weight": 1.0}, {"source": "syllabus_route_get", "target": "auth_require_role_requireschoolmember", "relation": "calls", "confidence": "EXTRACTED", "confidence_score": 1.0, "source_file": "web/app/api/syllabus/route.ts", "source_location": null, "weight": 1.0}], "hyperedges": []}